CHANGES.rst
MANIFEST.in
README.rst
requirements.txt
setup.py
bin/playdeliver
playdeliver/__init__.py
playdeliver/client.py
playdeliver/file_util.py
playdeliver/image.py
playdeliver/inapp_product.py
playdeliver/listing.py
playdeliver/playdeliver.py
playdeliver/sync_command.py
playdeliver.egg-info/PKG-INFO
playdeliver.egg-info/SOURCES.txt
playdeliver.egg-info/dependency_links.txt
playdeliver.egg-info/requires.txt
playdeliver.egg-info/top_level.txt