Metadata-Version: 1.1
Name: playdeliver
Version: 1.1.1
Summary: google play store delivering tool
Home-page: https://github.com/wooga/play-deliver
Author: Manfred Endres
Author-email: manfred.endres@wooga.net
License: MIT LICENSE
Download-URL: https://github.com/wooga/play-deliver/archive/1.1.1.tar.gz
Platform: any
Classifier: Programming Language :: Python :: 2 :: Only
Classifier: Development Status :: 5 - Production/Stable
Classifier: Natural Language :: English
Classifier: Environment :: MacOS X
Classifier: Intended Audience :: Developers
Classifier: License :: OSI Approved :: MIT License
Classifier: Operating System :: MacOS :: MacOS X
Classifier: Topic :: Multimedia :: Graphics
Classifier: Topic :: System :: Archiving :: Packaging
Classifier: Topic :: Software Development :: Libraries :: Python Modules
